empowernow_common/__init__.py
empowernow_common/arn.py
empowernow_common/aud.py
empowernow_common/errors.py
empowernow_common/exceptions.py
empowernow_common/identity.py
empowernow_common/kafka_audit.py
empowernow_common/py.typed
empowernow_common/settings.py
empowernow_common/auth/__init__.py
empowernow_common/auth/loopback_signer.py
empowernow_common/auth/principal.py
empowernow_common/authzen/__init__.py
empowernow_common/authzen/client.py
empowernow_common/authzen/config.py
empowernow_common/authzen/helpers.py
empowernow_common/authzen/metrics.py
empowernow_common/authzen/models.py
empowernow_common/authzen/secure_client.py
empowernow_common/authzen/secure_client_v2.py
empowernow_common/cache/__init__.py
empowernow_common/cache/redis_backend.py
empowernow_common/client/__init__.py
empowernow_common/delegation/__init__.py
empowernow_common/delegation/cache.py
empowernow_common/delegation/capability.py
empowernow_common/delegation/events.py
empowernow_common/delegation/exceptions.py
empowernow_common/delegation/metering.py
empowernow_common/delegation/models.py
empowernow_common/delegation/registry.py
empowernow_common/delegation/token.py
empowernow_common/delegation/verifier.py
empowernow_common/denial/__init__.py
empowernow_common/denial/reasons.py
empowernow_common/denial/response.py
empowernow_common/examples/__init__.py
empowernow_common/examples/fastapi_demo.py
empowernow_common/fastapi/__init__.py
empowernow_common/fips/__init__.py
empowernow_common/fips/algorithms.py
empowernow_common/fips/entropy.py
empowernow_common/fips/validator.py
empowernow_common/jwt/__init__.py
empowernow_common/jwt/config.py
empowernow_common/jwt/errors.py
empowernow_common/jwt/factory.py
empowernow_common/jwt/lightweight_validator.py
empowernow_common/jwt/utils.py
empowernow_common/jwt/validators.py
empowernow_common/kafka/platform_producer.py
empowernow_common/kafka/topics.py
empowernow_common/mcp/__init__.py
empowernow_common/mcp/servers.py
empowernow_common/mcp/tool_id.py
empowernow_common-3.4.1.dist-info/METADATA
empowernow_common-3.4.1.dist-info/WHEEL
empowernow_common-3.4.1.dist-info/entry_points.txt
empowernow_common-3.4.1.dist-info/top_level.txt
empowernow_common-3.4.1.dist-info/RECORD
