Metadata-Version: 2.4
Name: empowernow-common
Version: 3.4.1
Summary: Common utilities and FIPS-compliant cryptography for EmpowerNow packages
Author-email: EmpowerNow <support@empowernow.io>
License: MIT
Project-URL: Homepage, https://github.com/EmpowerNowAI/python-sdk
Project-URL: Documentation, https://github.com/EmpowerNowAI/python-sdk#readme
Project-URL: Repository, https://github.com/EmpowerNowAI/python-sdk
Project-URL: Issues, https://github.com/EmpowerNowAI/python-sdk/issues
Classifier: Development Status :: 4 - Beta
Classifier: Intended Audience :: Developers
Classifier: Topic :: Security :: Cryptography
Classifier: Topic :: Software Development :: Libraries :: Python Modules
Classifier: License :: OSI Approved :: MIT License
Classifier: Programming Language :: Python :: 3
Classifier: Programming Language :: Python :: 3.10
Classifier: Programming Language :: Python :: 3.11
Classifier: Programming Language :: Python :: 3.12
Classifier: Operating System :: OS Independent
Requires-Python: >=3.10
Requires-Dist: cryptography<43,~=41.0
Requires-Dist: pydantic<3.0,~=2.5
Requires-Dist: pydantic-settings<3.0,>=2.4
Requires-Dist: fastapi<1,>=0.115
Requires-Dist: httpx<1,>=0.28
Requires-Dist: anyio<5.0,>=3.7
Requires-Dist: trio<0.30
Requires-Dist: structlog<26,>=24
Requires-Dist: cachetools<6,>=5
Requires-Dist: pyjwt>=2.8
Requires-Dist: pyyaml>=6.0
Requires-Dist: tenacity<10,>=8.2
Requires-Dist: opentelemetry-api>=1.20
Provides-Extra: fips
Requires-Dist: cryptography[fips]>=41.0.0; extra == "fips"
Requires-Dist: pyopenssl>=23.0.0; extra == "fips"
Provides-Extra: dev
Requires-Dist: pytest>=7.0.0; extra == "dev"
Requires-Dist: pytest-asyncio>=0.21.0; extra == "dev"
Requires-Dist: pytest-cov>=4.0.0; extra == "dev"
Requires-Dist: trio>=0.25; extra == "dev"
Requires-Dist: black>=23.0.0; extra == "dev"
Requires-Dist: isort>=5.0.0; extra == "dev"
Requires-Dist: mypy>=1.0.0; extra == "dev"
Requires-Dist: flake8>=6.0.0; extra == "dev"
Requires-Dist: pre-commit>=3.0.0; extra == "dev"
Requires-Dist: respx>=0.21; extra == "dev"
Provides-Extra: docs
Requires-Dist: mkdocs>=1.5.0; extra == "docs"
Requires-Dist: mkdocs-material>=9.0.0; extra == "docs"
Requires-Dist: mkdocstrings[python]>=0.22.0; extra == "docs"
Provides-Extra: fastapi
Requires-Dist: fastapi<1,>=0.115; extra == "fastapi"
Requires-Dist: python-jose[cryptography]>=3.3; extra == "fastapi"
Requires-Dist: pyyaml>=6.0; extra == "fastapi"
Requires-Dist: httpx<1,>=0.28; extra == "fastapi"
Provides-Extra: redis
Requires-Dist: redis<6.0,~=5.0; extra == "redis"
Provides-Extra: kafka
Requires-Dist: kafka-python~=2.0; extra == "kafka"
Provides-Extra: metrics
Requires-Dist: prometheus-client<0.20,~=0.17; extra == "metrics"
Provides-Extra: events
Requires-Dist: kafka-python~=2.0; extra == "events"
Requires-Dist: httpx>=0.25; extra == "events"
Provides-Extra: cli
Requires-Dist: click<9.0,>=8.0; extra == "cli"
Requires-Dist: rich<14.0,>=13.0; extra == "cli"
Provides-Extra: vault
Requires-Dist: azure-keyvault-secrets<5,>=4.7; extra == "vault"
Requires-Dist: azure-identity<2,>=1.15; extra == "vault"
